AUTHORS.rst
CONTRIBUTING.rst
HISTORY.rst
LICENSE
MANIFEST.in
README.rst
setup.cfg
setup.py
buildout/__init__.py
buildout.recipe.mako_template.egg-info/PKG-INFO
buildout.recipe.mako_template.egg-info/SOURCES.txt
buildout.recipe.mako_template.egg-info/dependency_links.txt
buildout.recipe.mako_template.egg-info/entry_points.txt
buildout.recipe.mako_template.egg-info/namespace_packages.txt
buildout.recipe.mako_template.egg-info/not-zip-safe
buildout.recipe.mako_template.egg-info/requires.txt
buildout.recipe.mako_template.egg-info/top_level.txt
buildout/recipe/__init__.py
buildout/recipe/mako_template/__init__.py
buildout/recipe/mako_template/recipe.py
tests/conftest.py
tests/test_acceptance.py
tests/test_unit.py
tests/buildout/buildout.cfg
tests/buildout/templates/bash_script.mako
tests/buildout/templates/buildout_parts_are_accessible_in_tempate.mako
tests/buildout/templates/simple-test-template.mako
tests/buildout/templates/base/inerit-test-base-template.mako
tests/buildout/templates/child/inerit-test-template-directories-lookup.mako
tests/buildout/templates/child/inerit-test-template.mako