Metadata-Version: 1.1
Name: buildout.recipe.mako-template
Version: 0.1.2
Summary: Buildout recipe for making files out of Mako templates
Home-page: https://github.com/enkidulan/buildout.recipe.mako_template
Author: Maksym Shalenyi
Author-email: maksym.shalenyi@gmail.com
License: MIT license
Keywords: buildout recipe mako template
Platform: UNKNOWN
Classifier: Development Status :: 2 - Pre-Alpha
Classifier: Intended Audience :: Developers
Classifier: License :: OSI Approved :: MIT License
Classifier: Natural Language :: English
Classifier: Programming Language :: Python :: 2
Classifier: Programming Language :: Python :: 2.7
Classifier: Programming Language :: Python :: 3
Classifier: Programming Language :: Python :: 3.4
Classifier: Programming Language :: Python :: 3.5
Classifier: Programming Language :: Python :: 3.6
